shinyOdds/__init__.py
shinyOdds/calcShiny.py
shinyOdds/shinyOdds.py
streamEnder/__init__.py
streamEnder/streamEnder.py
twitchBot/__init__.py
twitchBot/bot.py
twitchBot/botCommands.py
pokemonStreamTools-0.1.6.dist-info/LICENSE
pokemonStreamTools-0.1.6.dist-info/METADATA
pokemonStreamTools-0.1.6.dist-info/WHEEL
pokemonStreamTools-0.1.6.dist-info/entry_points.txt
pokemonStreamTools-0.1.6.dist-info/top_level.txt
pokemonStreamTools-0.1.6.dist-info/RECORD
