Metadata-Version: 2.1
Name: pokemonStreamTools
Version: 0.1.6
Summary: Tools for streaming pokemon
Home-page: https://github.com/drkspace/Pokemon-Stream-Tools
Author: Daniel Kramer
Author-email: drkspace@gmail.com
License: UNKNOWN
Project-URL: Bug Tracker, https://github.com/drkspace/Pokemon-Stream-Tools/issues
Platform: UNKNOWN
Classifier: Programming Language :: Python :: 3
Classifier: License :: OSI Approved :: MIT License
Classifier: Operating System :: OS Independent
Requires-Python: >=3.6
License-File: LICENSE
Requires-Dist: scipy (~=1.7.1)
Requires-Dist: numpy (~=1.21.4)
Requires-Dist: matplotlib (~=3.4.3)
Requires-Dist: watchdog (~=2.1.3)
Requires-Dist: obs-websocket-py (~=0.5.3)
Requires-Dist: twitchio (~=2.2.0)
